django_di/__init__.py
django_di/context.py
django_di/view.py
django_di-0.0.3.dist-info/LICENSE
django_di-0.0.3.dist-info/METADATA
django_di-0.0.3.dist-info/WHEEL
django_di-0.0.3.dist-info/top_level.txt
django_di-0.0.3.dist-info/RECORD
